Workbook

Sheet Instructions
A1: eDining Manual Billing System
A2: Complete Spreadsheet Template for Muktijoddha Hall - June 2026
A4: Overview
A5: This spreadsheet allows dining managers to log deposits, bazaar expenses, and daily meal attendance manually. It uses Excel formulas to calculate home meal units, guest contributions, daily manager fees, and the dynamically settled meal rate. The calculations mirror the eDining web application.
A7: Sheet Descriptions
A8: Instructions | B8: This user guide and reference sheet.
A9: Setup | B9: Contains constants: Guest rates, Daily manager fees, Lunch/Dinner weights.
A10: Dashboard | B10: Summarizes total system financial health, including calculated meal rates and totals.
A11: Members & Balances | B11: The central ledger. Computes every member's balance, billing, and settlements using formulas.
A12: Expenses | B12: Log daily bazaar expenses here. Column E accumulates into the total expense.
A13: Deposits | B13: Log student payments (Cash or bKash) here. Automatically links to the member list.
A14: Meals Grid | B14: Record student meals for each day. Use standard codes (B, L, D, GB, GL, GD) to mark attendance.
A16: Meal Codes for Meals Grid
A18: Code | B18: Meal Type | C18: Calculation Rule
A19: B | B19: Home Student Both Meals | C19: Counts as 1.0 Meal Unit. Subject to manager charges.
A20: L | B20: Home Student Lunch Only | C20: Counts as Lunch Weight (default 0.50). Subject to manager charges.
A21: D | B21: Home Student Dinner Only | C21: Counts as Dinner Weight (default 0.50). Subject to manager charges.
A22: GB | B22: Guest Both Meals | C22: Charged at flat Guest Meal Rate. No manager fee.
A23: GL | B23: Guest Lunch Only | C23: Charged at Guest Rate * Lunch Weight. No manager fee.
A24: GD | B24: Guest Dinner Only | C24: Charged at Guest Rate * Dinner Weight. No manager fee.
A25: O / Blank | B25: No Meals (Off) | C25: No meal units, no charges, no manager fees.
A27: Important Notes:
A28: 1. Do NOT modify columns in 'Members & Balances' containing formulas. These columns have headers styled differently.
A29: 2. When adding a new student, insert them in both 'Members & Balances' and 'Meals Grid' with matching Member IDs.
A30: 3. Ensure the active month dates in 'Meals Grid' correspond to the number of days in the billing month.

Sheet Setup
A1: eDining System Configurations
A2: Variables defined here are referenced throughout the sheets.
A4: Parameter | B4: Value
A5: Hall Name | B5: Muktijoddha Hall
A6: Billing Month | B6: 2026-06
A7: Guest Meal Rate (BDT) | B7: 120
A8: Manager Daily Fee (BDT) | B8: 5
A9: Lunch Weight Percentage | B9: 0.5
A10: Dinner Weight Percentage | B10: 0.5

Sheet Dashboard
B2: eDining Monthly Summary Dashboard
B3: Active System Statistics for Muktijoddha Hall - June 2026
B4: Financial Metric | C4: Value (Calculated by Formulas)
B5: Total System Expenses | C5: =SUM(Expenses!$E$7:$E$1000)
B6: Total Guest Contributions | C6: =SUM('Members & Balances'!$J$10:$J$1000)
B7: Net System Expenses | C7: =MAX(0, C5-C6)
B8: Total Home Meal Units | C8: =SUM('Members & Balances'!$H$10:$H$1000)
B9: Calculated Meal Rate | C9: =IF(C8>0, C7/C8, 0)
B10: Total Manager Fees Collected | C10: =SUM('Members & Balances'!$K$10:$K$1000)
B11: Total Deposits Received | C11: =SUM(Deposits!$D$7:$D$1000)
B12: Outstanding Settlement Adjustments | C12: =SUM('Members & Balances'!$O$10:$O$1000)-SUM('Members & Balances'!$G$10:$G$1000)

Sheet Meals Grid
A1: Daily Meal Attendance Grid
A2: Mark meals for June 2026. Codes: B (Both), L (Lunch), D (Dinner), GB (Guest Both), GL (Guest Lunch), GD (Guest Dinner), O (Off)
A7: Member ID | B7: Name | C7: Role | D7: 1 | E7: 2 | F7: 3 | G7: 4 | H7: 5 | I7: 6 | J7: 7 | K7: 8 | L7: 9 | M7: 10 | N7: 11 | O7: 12 | P7: 13 | Q7: 14 | R7: 15 | S7: 16 | T7: 17 | U7: 18 | V7: 19 | W7: 20 | X7: 21 | Y7: 22 | Z7: 23 | AA7: 24 | AB7: 25 | AC7: 26 | AD7: 27 | AE7: 28 | AF7: 29 | AG7: 30 | AH7: Lunch (L) | AI7: Dinner (D) | AJ7: Both (B) | AK7: Guest Lunch (GL) | AL7: Guest Dinner (GD) | AM7: Guest Both (GB) | AN7: Home Meal Units | AO7: Active Days | AP7: Guest Meal Units
A8: 1 | B8: System Super Admin | C8: superadmin | AH8: =COUNTIF(D8:AG8, "L") | AI8: =COUNTIF(D8:AG8, "D") | AJ8: =COUNTIF(D8:AG8, "B") | AK8: =COUNTIF(D8:AG8, "GL") | AL8: =COUNTIF(D8:AG8, "GD") | AM8: =COUNTIF(D8:AG8, "GB") | AN8: =AJ8+(AH8*Setup!$B$8)+(AI8*Setup!$B$9) | AO8: =COUNTIF(D8:AG8, "L")+COUNTIF(D8:AG8, "D")+COUNTIF(D8:AG8, "B") | AP8: =AM8+(AK8*Setup!$B$8)+(AL8*Setup!$B$9)
A9: 4 | B9: Kamrul Islam | C9: student | S9: B | T9: B | U9: B | V9: B | W9: B | X9: B | Y9: B | Z9: B | AA9: B | AB9: B | AC9: B | AD9: B | AE9: B | AF9: B | AG9: B | AH9: =COUNTIF(D9:AG9, "L") | AI9: =COUNTIF(D9:AG9, "D") | AJ9: =COUNTIF(D9:AG9, "B") | AK9: =COUNTIF(D9:AG9, "GL") | AL9: =COUNTIF(D9:AG9, "GD") | AM9: =COUNTIF(D9:AG9, "GB") | AN9: =AJ9+(AH9*Setup!$B$8)+(AI9*Setup!$B$9) | AO9: =COUNTIF(D9:AG9, "L")+COUNTIF(D9:AG9, "D")+COUNTIF(D9:AG9, "B") | AP9: =AM9+(AK9*Setup!$B$8)+(AL9*Setup!$B$9)
A10: 5 | B10: Rakib Hasan | C10: student | AH10: =COUNTIF(D10:AG10, "L") | AI10: =COUNTIF(D10:AG10, "D") | AJ10: =COUNTIF(D10:AG10, "B") | AK10: =COUNTIF(D10:AG10, "GL") | AL10: =COUNTIF(D10:AG10, "GD") | AM10: =COUNTIF(D10:AG10, "GB") | AN10: =AJ10+(AH10*Setup!$B$8)+(AI10*Setup!$B$9) | AO10: =COUNTIF(D10:AG10, "L")+COUNTIF(D10:AG10, "D")+COUNTIF(D10:AG10, "B") | AP10: =AM10+(AK10*Setup!$B$8)+(AL10*Setup!$B$9)
A11: 2 | B11: Sabbir Ahmed (Mukti Mgr) | C11: manager | S11: B | T11: B | U11: B | V11: B | W11: B | X11: B | Y11: B | Z11: B | AA11: B | AB11: B | AC11: B | AD11: B | AE11: B | AF11: B | AG11: B | AH11: =COUNTIF(D11:AG11, "L") | AI11: =COUNTIF(D11:AG11, "D") | AJ11: =COUNTIF(D11:AG11, "B") | AK11: =COUNTIF(D11:AG11, "GL") | AL11: =COUNTIF(D11:AG11, "GD") | AM11: =COUNTIF(D11:AG11, "GB") | AN11: =AJ11+(AH11*Setup!$B$8)+(AI11*Setup!$B$9) | AO11: =COUNTIF(D11:AG11, "L")+COUNTIF(D11:AG11, "D")+COUNTIF(D11:AG11, "B") | AP11: =AM11+(AK11*Setup!$B$8)+(AL11*Setup!$B$9)
A12: 7 | B12: khoka moni | C12: manager | S12: B | T12: B | U12: B | V12: B | W12: B | X12: B | Y12: B | Z12: B | AA12: B | AB12: B | AC12: B | AD12: B | AE12: B | AF12: B | AG12: B | AH12: =COUNTIF(D12:AG12, "L") | AI12: =COUNTIF(D12:AG12, "D") | AJ12: =COUNTIF(D12:AG12, "B") | AK12: =COUNTIF(D12:AG12, "GL") | AL12: =COUNTIF(D12:AG12, "GD") | AM12: =COUNTIF(D12:AG12, "GB") | AN12: =AJ12+(AH12*Setup!$B$8)+(AI12*Setup!$B$9) | AO12: =COUNTIF(D12:AG12, "L")+COUNTIF(D12:AG12, "D")+COUNTIF(D12:AG12, "B") | AP12: =AM12+(AK12*Setup!$B$8)+(AL12*Setup!$B$9)

Sheet Members & Balances
A1: Member Ledger & Balance Sheet
A2: Active Ledger for Muktijoddha Hall - June 2026
A4: Note: Columns in Teal (H, I, J, K, L, M, N, O) contain EXCEL FORMULAS. Do not manually edit them.
A9: Member ID | B9: Name | C9: Room No | D9: Phone No | E9: Role | F9: Free Meal? | G9: Opening Balance (BDT) | H9: Home Meal Units | I9: Active Days | J9: Guest Meal Cost (BDT) | K9: Manager Fees (BDT) | L9: Meal Cost (BDT) | M9: Total Deposits (BDT) | N9: Total Bill (BDT) | O9: Closing Balance (BDT)
A10: 1 | B10: System Super Admin | D10: 01711223344 | E10: superadmin | F10: No | G10: 0 | H10: =IFERROR(VLOOKUP(A10, 'Meals Grid'!$A$8:$AP$1000, 40, FALSE), 0) | I10: =IFERROR(VLOOKUP(A10, 'Meals Grid'!$A$8:$AP$1000, 41, FALSE), 0) | J10: =IFERROR(VLOOKUP(A10, 'Meals Grid'!$A$8:$AP$1000, 42, FALSE), 0) * Setup!$B$6 | K10: =IF(F10="Yes", 0, I10 * Setup!$B$7) | L10: =IF(F10="Yes", 0, H10 * Dashboard!$C$9) | M10: =SUMIF(Deposits!$B$7:$B$1000, A10, Deposits!$D$7:$D$1000) | N10: =J10+K10+L10 | O10: =G10+M10-N10
A11: 4 | B11: Kamrul Islam | C11: 102 | D11: 01511223344 | E11: student | F11: No | G11: 1500 | H11: =IFERROR(VLOOKUP(A11, 'Meals Grid'!$A$8:$AP$1000, 40, FALSE), 0) | I11: =IFERROR(VLOOKUP(A11, 'Meals Grid'!$A$8:$AP$1000, 41, FALSE), 0) | J11: =IFERROR(VLOOKUP(A11, 'Meals Grid'!$A$8:$AP$1000, 42, FALSE), 0) * Setup!$B$6 | K11: =IF(F11="Yes", 0, I11 * Setup!$B$7) | L11: =IF(F11="Yes", 0, H11 * Dashboard!$C$9) | M11: =SUMIF(Deposits!$B$7:$B$1000, A11, Deposits!$D$7:$D$1000) | N11: =J11+K11+L11 | O11: =G11+M11-N11
A12: 5 | B12: Rakib Hasan | C12: 103 | D12: 01611223344 | E12: student | F12: No | G12: 2000 | H12: =IFERROR(VLOOKUP(A12, 'Meals Grid'!$A$8:$AP$1000, 40, FALSE), 0) | I12: =IFERROR(VLOOKUP(A12, 'Meals Grid'!$A$8:$AP$1000, 41, FALSE), 0) | J12: =IFERROR(VLOOKUP(A12, 'Meals Grid'!$A$8:$AP$1000, 42, FALSE), 0) * Setup!$B$6 | K12: =IF(F12="Yes", 0, I12 * Setup!$B$7) | L12: =IF(F12="Yes", 0, H12 * Dashboard!$C$9) | M12: =SUMIF(Deposits!$B$7:$B$1000, A12, Deposits!$D$7:$D$1000) | N12: =J12+K12+L12 | O12: =G12+M12-N12
A13: 2 | B13: Sabbir Ahmed (Mukti Mgr) | C13: 302 | D13: 01911223344 | E13: manager | F13: Yes | G13: 1566 | H13: =IFERROR(VLOOKUP(A13, 'Meals Grid'!$A$8:$AP$1000, 40, FALSE), 0) | I13: =IFERROR(VLOOKUP(A13, 'Meals Grid'!$A$8:$AP$1000, 41, FALSE), 0) | J13: =IFERROR(VLOOKUP(A13, 'Meals Grid'!$A$8:$AP$1000, 42, FALSE), 0) * Setup!$B$6 | K13: =IF(F13="Yes", 0, I13 * Setup!$B$7) | L13: =IF(F13="Yes", 0, H13 * Dashboard!$C$9) | M13: =SUMIF(Deposits!$B$7:$B$1000, A13, Deposits!$D$7:$D$1000) | N13: =J13+K13+L13 | O13: =G13+M13-N13
A14: 7 | B14: khoka moni | C14: 208 | D14: 01521769018 | E14: manager | F14: No | G14: 1000 | H14: =IFERROR(VLOOKUP(A14, 'Meals Grid'!$A$8:$AP$1000, 40, FALSE), 0) | I14: =IFERROR(VLOOKUP(A14, 'Meals Grid'!$A$8:$AP$1000, 41, FALSE), 0) | J14: =IFERROR(VLOOKUP(A14, 'Meals Grid'!$A$8:$AP$1000, 42, FALSE), 0) * Setup!$B$6 | K14: =IF(F14="Yes", 0, I14 * Setup!$B$7) | L14: =IF(F14="Yes", 0, H14 * Dashboard!$C$9) | M14: =SUMIF(Deposits!$B$7:$B$1000, A14, Deposits!$D$7:$D$1000) | N14: =J14+K14+L14 | O14: =G14+M14-N14
B15: Total | G15: =SUM(G10:G14) | H15: =SUM(H10:H14) | I15: =SUM(I10:I14) | J15: =SUM(J10:J14) | K15: =SUM(K10:K14) | L15: =SUM(L10:L14) | M15: =SUM(M10:M14) | N15: =SUM(N10:N14) | O15: =SUM(O10:O14)

Sheet Expenses
A1: Bazaar Expense Ledger
A2: Log daily purchases for June 2026.
A6: Date | B6: Item Description | C6: Quantity | D6: Unit | E6: Amount (BDT)
A7: 2026-06-15 | B7: rice | C7: 2 | D7: kg | E7: 155
A8: 2026-06-15 | B8: murgi | C8: 10 | D8: kg | E8: 5000
B30: Total Expenses | E30: =SUM(E7:E29)

Sheet Deposits
A1: Student Deposit Ledger
A2: Log student meal payments (Cash / Bank / bKash) for June 2026.
A4: Note: Column C (Name) contains an EXCEL FORMULA. It will auto-fill when you type a valid Member ID.
A6: Date | B6: Member ID | C6: Name (Auto) | D6: Amount (BDT) | E6: Description / Transaction Ref
A7: 2026-06-15 | B7: 7 | C7: =IFERROR(VLOOKUP(B7, 'Members & Balances'!$A$10:$B$1000, 2, FALSE), "") | D7: 1000 | E7: cash
A8: 2026-06-15 | B8: 2 | C8: =IFERROR(VLOOKUP(B8, 'Members & Balances'!$A$10:$B$1000, 2, FALSE), "") | D8: 500 | E8: bKash Send Money (Sender: 01711223344, TrxID: ZZCNQOFS27)
A9: 2026-06-15 | B9: 2 | C9: =IFERROR(VLOOKUP(B9, 'Members & Balances'!$A$10:$B$1000, 2, FALSE), "") | D9: 566 | E9: bKash Send Money (Sender: Manager, TrxID: FSDFSADFWE)
C10: =IFERROR(VLOOKUP(B10, 'Members & Balances'!$A$10:$B$1000, 2, FALSE), "")
C11: =IFERROR(VLOOKUP(B11, 'Members & Balances'!$A$10:$B$1000, 2, FALSE), "")
C12: =IFERROR(VLOOKUP(B12, 'Members & Balances'!$A$10:$B$1000, 2, FALSE), "")
C13: =IFERROR(VLOOKUP(B13, 'Members & Balances'!$A$10:$B$1000, 2, FALSE), "")
C14: =IFERROR(VLOOKUP(B14, 'Members & Balances'!$A$10:$B$1000, 2, FALSE), "")
C15: =IFERROR(VLOOKUP(B15, 'Members & Balances'!$A$10:$B$1000, 2, FALSE), "")
C16: =IFERROR(VLOOKUP(B16, 'Members & Balances'!$A$10:$B$1000, 2, FALSE), "")
C17: =IFERROR(VLOOKUP(B17, 'Members & Balances'!$A$10:$B$1000, 2, FALSE), "")
C18: =IFERROR(VLOOKUP(B18, 'Members & Balances'!$A$10:$B$1000, 2, FALSE), "")
C19: =IFERROR(VLOOKUP(B19, 'Members & Balances'!$A$10:$B$1000, 2, FALSE), "")
C20: =IFERROR(VLOOKUP(B20, 'Members & Balances'!$A$10:$B$1000, 2, FALSE), "")
C21: =IFERROR(VLOOKUP(B21, 'Members & Balances'!$A$10:$B$1000, 2, FALSE), "")
... C29: =IFERROR(VLOOKUP(B29, 'Members & Balances'!$A$10:$B$1000, 2, FALSE), "")
B30: Total Deposits | D30: =SUM(D7:D29)
