Workbook

Sheet Lists
A1: Roles | B1: YesNo | C1: MealCodes
A2: superadmin | B2: Yes | C2: B
A3: manager | B3: No | C3: L
A4: assistant_manager | C4: D
A5: staff | C5: GB
A6: student | C6: GL
C7: GD
C8: O

Sheet Instructions
A1: eDining Advanced Manual Billing System
A2: Dynamic Start/End Date Ledger Template for Muktijoddha Hall
A3: =HYPERLINK("#'Instructions'!A1", "📖 Instructions") | C3: =HYPERLINK("#'Setup'!A1", "⚙️ Setup") | E3: =HYPERLINK("#'Dashboard'!A1", "📊 Dashboard") | G3: =HYPERLINK("#'Meals Grid'!A1", "🍽️ Meals Grid") | I3: =HYPERLINK("#'Members & Balances'!A1", "👥 Members") | K3: =HYPERLINK("#'Expenses'!A1", "🛒 Expenses") | M3: =HYPERLINK("#'Deposits'!A1", "💰 Deposits") | O3: =HYPERLINK("#'bKash Transactions'!A1", "📱 bKash Audit")
A5: Overview & System Controls
A6: This version is fully dynamic, parameterized, and structured for zero-hardcoding. It features an app-like navigation bar, dropdown data validations to prevent typos, automatic weekend/inactive date formatting, and advanced audit verification tables.
A8: Advanced Controls Built-In
A9: Navigation Bar | B9: Click the links on Row 3 of any sheet to quickly navigate between sheets (app-like experience).
A10: Dropdown Dropdowns | B10: Cells in Roles, Free Meal, Meals Grid, and Deposit IDs are wired with dropdowns. You cannot enter invalid values.
A11: Dynamic Calendars | B11: Weekends (Sat/Sun) and Inactive days are highlighted automatically using Excel Conditional Formatting.
A12: bKash Audit verification | B12: SMS transactions are compared with Deposits. If a matching ID has incorrect value, 'Amount Mismatch!' is shown.
A14: System Meal Codes Reference
A16: Code | B16: Meal Type | C16: Calculation Rule
A17: B | B17: Home Student Both Meals | C17: Counts as 1.0 Meal Unit. Subject to daily manager fees.
A18: L | B18: Home Student Lunch Only | C18: Counts as Lunch Weight (Setup!C11). Subject to daily manager fees.
A19: D | B19: Home Student Dinner Only | C19: Counts as Dinner Weight (Setup!C12). Subject to daily manager fees.
A20: GB | B20: Guest Both Meals | C20: Charged at flat Guest Meal Rate. Exempt from manager fees.
A21: GL | B21: Guest Lunch Only | C21: Charged at Guest Rate * Lunch Weight. Exempt from manager fees.
A22: GD | B22: Guest Dinner Only | C22: Charged at Guest Rate * Dinner Weight. Exempt from manager fees.
A23: O / Blank | B23: No Meals (Off) | C23: No meal units, no charges, no manager fees.

Sheet Setup
A1: System Parameter Configuration
A2: Define billing period dates and system rates here. All other tabs dynamically read from this.
A3: =HYPERLINK("#'Instructions'!A1", "📖 Instructions") | C3: =HYPERLINK("#'Setup'!A1", "⚙️ Setup") | E3: =HYPERLINK("#'Dashboard'!A1", "📊 Dashboard") | G3: =HYPERLINK("#'Meals Grid'!A1", "🍽️ Meals Grid") | I3: =HYPERLINK("#'Members & Balances'!A1", "👥 Members") | K3: =HYPERLINK("#'Expenses'!A1", "🛒 Expenses") | M3: =HYPERLINK("#'Deposits'!A1", "💰 Deposits") | O3: =HYPERLINK("#'bKash Transactions'!A1", "📱 bKash Audit")
B5: Parameter | C5: Value
B6: Hall Name | C6: Muktijoddha Hall
B7: Cycle Start Date | C7: 2026-06-15
B8: Cycle End Date | C8: 2026-06-30
B9: Cycle Total Days | C9: =C8-C7+1
B10: Guest Meal Rate (BDT) | C10: 120
B11: Manager Daily Fee (BDT) | C11: 5
B12: Lunch Weight Percentage | C12: 0.5
B13: Dinner Weight Percentage | C13: 0.5

Sheet Dashboard
B2: eDining Monthly Summary Dashboard
A3: =HYPERLINK("#'Instructions'!A1", "📖 Instructions") | C3: =HYPERLINK("#'Setup'!A1", "⚙️ Setup") | E3: =HYPERLINK("#'Dashboard'!A1", "📊 Dashboard") | G3: =HYPERLINK("#'Meals Grid'!A1", "🍽️ Meals Grid") | I3: =HYPERLINK("#'Members & Balances'!A1", "👥 Members") | K3: =HYPERLINK("#'Expenses'!A1", "🛒 Expenses") | M3: =HYPERLINK("#'Deposits'!A1", "💰 Deposits") | O3: =HYPERLINK("#'bKash Transactions'!A1", "📱 bKash Audit")
B4: Financial Metric | C4: Value (Calculated by Formulas)
B5: Total System Expenses | C5: =SUM(Expenses!$E$7:$E$1000)
B6: Total Guest Contributions | C6: =SUM('Members & Balances'!$J$10:$J$1000)
B7: Net System Expenses | C7: =MAX(0, C5-C6)
B8: Total Home Meal Units | C8: =SUM('Members & Balances'!$H$10:$H$1000)
B9: Calculated Meal Rate | C9: =IF(C8>0, C7/C8, 0)
B10: Total Manager Fees Collected | C10: =SUM('Members & Balances'!$K$10:$K$1000)
B11: Total Deposits Received | C11: =SUM(Deposits!$D$7:$D$1000)
B12: Outstanding Settlement Adjustments | C12: =SUM('Members & Balances'!$O$10:$O$1000)-SUM('Members & Balances'!$G$10:$G$1000)
B15: System Integrity & Solvency Auditor
B16: Solvency Check (Deposits vs Billings) | C16: =C11-SUM('Members & Balances'!$N$10:$N$1000)
B17: Unclaimed bKash SMS Count | C17: =COUNTIF('bKash Transactions'!$H$7:$H$1000, "Unclaimed")
B18: Amount Mismatch Alerts | C18: =COUNTIF('bKash Transactions'!$I$7:$I$1000, "Amount Mismatch!")
B19: System Status Report | C19: =IF(C18>0, "🚨 Warning: Mismatch Found!", IF(C16<0, "⚠️ Warning: System Insolvency", "✅ Healthy"))

Sheet Meals Grid
A1: Daily Meal Attendance Grid
A2: Log meals. Codes: B (Both), L (Lunch), D (Dinner), GB (Guest Both), GL (Guest Lunch), GD (Guest Dinner), O (Off)
A3: =HYPERLINK("#'Instructions'!A1", "📖 Instructions") | C3: =HYPERLINK("#'Setup'!A1", "⚙️ Setup") | E3: =HYPERLINK("#'Dashboard'!A1", "📊 Dashboard") | G3: =HYPERLINK("#'Meals Grid'!A1", "🍽️ Meals Grid") | I3: =HYPERLINK("#'Members & Balances'!A1", "👥 Members") | K3: =HYPERLINK("#'Expenses'!A1", "🛒 Expenses") | M3: =HYPERLINK("#'Deposits'!A1", "💰 Deposits") | O3: =HYPERLINK("#'bKash Transactions'!A1", "📱 bKash Audit")
A5: Day of Week | D5: =IF(D6="","",TEXT(D6,"ddd")) | E5: =IF(E6="","",TEXT(E6,"ddd")) | F5: =IF(F6="","",TEXT(F6,"ddd")) | G5: =IF(G6="","",TEXT(G6,"ddd")) | H5: =IF(H6="","",TEXT(H6,"ddd")) | I5: =IF(I6="","",TEXT(I6,"ddd")) | J5: =IF(J6="","",TEXT(J6,"ddd")) | K5: =IF(K6="","",TEXT(K6,"ddd")) | ... AI5: =IF(AI6="","",TEXT(AI6,"ddd"))
A6: Date | D6: =Setup!$C$7 | E6: =IF(D6="","",IF(D6+1<=Setup!$C$8,D6+1,"")) | F6: =IF(E6="","",IF(E6+1<=Setup!$C$8,E6+1,"")) | G6: =IF(F6="","",IF(F6+1<=Setup!$C$8,F6+1,"")) | H6: =IF(G6="","",IF(G6+1<=Setup!$C$8,G6+1,"")) | I6: =IF(H6="","",IF(H6+1<=Setup!$C$8,H6+1,"")) | J6: =IF(I6="","",IF(I6+1<=Setup!$C$8,I6+1,"")) | K6: =IF(J6="","",IF(J6+1<=Setup!$C$8,J6+1,"")) | L6: =IF(K6="","",IF(K6+1<=Setup!$C$8,K6+1,"")) | ... AI6: =IF(AH6="","",IF(AH6+1<=Setup!$C$8,AH6+1,""))
A7: Member ID | B7: Name | C7: Role | D7: Day 1 | E7: Day 2 | F7: Day 3 | G7: Day 4 | H7: Day 5 | I7: Day 6 | J7: Day 7 | K7: Day 8 | L7: Day 9 | M7: Day 10 | N7: Day 11 | O7: Day 12 | P7: Day 13 | Q7: Day 14 | R7: Day 15 | S7: Day 16 | T7: Day 17 | U7: Day 18 | V7: Day 19 | W7: Day 20 | X7: Day 21 | Y7: Day 22 | Z7: Day 23 | AA7: Day 24 | AB7: Day 25 | AC7: Day 26 | AD7: Day 27 | AE7: Day 28 | AF7: Day 29 | AG7: Day 30 | AH7: Day 31 | AI7: Day 32 | AJ7: Lunch (L) | AK7: Dinner (D) | AL7: Both (B) | AM7: Guest Lunch (GL) | AN7: Guest Dinner (GD) | AO7: Guest Both (GB) | AP7: Home Meal Units | AQ7: Active Days | AR7: Guest Meal Units
A8: 1 | B8: System Super Admin | C8: superadmin | AJ8: =COUNTIF(D8:AI8, "L") | AK8: =COUNTIF(D8:AI8, "D") | AL8: =COUNTIF(D8:AI8, "B") | AM8: =COUNTIF(D8:AI8, "GL") | AN8: =COUNTIF(D8:AI8, "GD") | AO8: =COUNTIF(D8:AI8, "GB") | AP8: =AL8+(AJ8*Setup!$C$11)+(AK8*Setup!$C$12) | AQ8: =COUNTIF(D8:AI8, "L")+COUNTIF(D8:AI8, "D")+COUNTIF(D8:AI8, "B") | AR8: =AO8+(AM8*Setup!$C$11)+(AN8*Setup!$C$12)
A9: 4 | B9: Kamrul Islam | C9: student | E9: B | F9: B | G9: B | H9: B | I9: B | J9: B | K9: B | L9: B | M9: B | N9: B | O9: B | P9: B | Q9: B | R9: B | S9: B | AJ9: =COUNTIF(D9:AI9, "L") | AK9: =COUNTIF(D9:AI9, "D") | AL9: =COUNTIF(D9:AI9, "B") | AM9: =COUNTIF(D9:AI9, "GL") | AN9: =COUNTIF(D9:AI9, "GD") | AO9: =COUNTIF(D9:AI9, "GB") | AP9: =AL9+(AJ9*Setup!$C$11)+(AK9*Setup!$C$12) | AQ9: =COUNTIF(D9:AI9, "L")+COUNTIF(D9:AI9, "D")+COUNTIF(D9:AI9, "B") | AR9: =AO9+(AM9*Setup!$C$11)+(AN9*Setup!$C$12)
A10: 5 | B10: Rakib Hasan | C10: student | AJ10: =COUNTIF(D10:AI10, "L") | AK10: =COUNTIF(D10:AI10, "D") | AL10: =COUNTIF(D10:AI10, "B") | AM10: =COUNTIF(D10:AI10, "GL") | AN10: =COUNTIF(D10:AI10, "GD") | AO10: =COUNTIF(D10:AI10, "GB") | AP10: =AL10+(AJ10*Setup!$C$11)+(AK10*Setup!$C$12) | AQ10: =COUNTIF(D10:AI10, "L")+COUNTIF(D10:AI10, "D")+COUNTIF(D10:AI10, "B") | AR10: =AO10+(AM10*Setup!$C$11)+(AN10*Setup!$C$12)
A11: 2 | B11: Sabbir Ahmed (Mukti Mgr) | C11: manager | E11: B | F11: B | G11: B | H11: B | I11: B | J11: B | K11: B | L11: B | M11: B | N11: B | O11: B | P11: B | Q11: B | R11: B | S11: B | AJ11: =COUNTIF(D11:AI11, "L") | AK11: =COUNTIF(D11:AI11, "D") | AL11: =COUNTIF(D11:AI11, "B") | AM11: =COUNTIF(D11:AI11, "GL") | AN11: =COUNTIF(D11:AI11, "GD") | AO11: =COUNTIF(D11:AI11, "GB") | AP11: =AL11+(AJ11*Setup!$C$11)+(AK11*Setup!$C$12) | AQ11: =COUNTIF(D11:AI11, "L")+COUNTIF(D11:AI11, "D")+COUNTIF(D11:AI11, "B") | AR11: =AO11+(AM11*Setup!$C$11)+(AN11*Setup!$C$12)
A12: 7 | B12: khoka moni | C12: manager | E12: B | F12: B | G12: B | H12: B | I12: B | J12: B | K12: B | L12: B | M12: B | N12: B | O12: B | P12: B | Q12: B | R12: B | S12: B | AJ12: =COUNTIF(D12:AI12, "L") | AK12: =COUNTIF(D12:AI12, "D") | AL12: =COUNTIF(D12:AI12, "B") | AM12: =COUNTIF(D12:AI12, "GL") | AN12: =COUNTIF(D12:AI12, "GD") | AO12: =COUNTIF(D12:AI12, "GB") | AP12: =AL12+(AJ12*Setup!$C$11)+(AK12*Setup!$C$12) | AQ12: =COUNTIF(D12:AI12, "L")+COUNTIF(D12:AI12, "D")+COUNTIF(D12:AI12, "B") | AR12: =AO12+(AM12*Setup!$C$11)+(AN12*Setup!$C$12)

Sheet Members & Balances
A1: Member Ledger & Balance Sheet
A2: Active Ledger for Muktijoddha Hall - Cycle (2026-06-15 to 2026-06-30)
A3: =HYPERLINK("#'Instructions'!A1", "📖 Instructions") | C3: =HYPERLINK("#'Setup'!A1", "⚙️ Setup") | E3: =HYPERLINK("#'Dashboard'!A1", "📊 Dashboard") | G3: =HYPERLINK("#'Meals Grid'!A1", "🍽️ Meals Grid") | I3: =HYPERLINK("#'Members & Balances'!A1", "👥 Members") | K3: =HYPERLINK("#'Expenses'!A1", "🛒 Expenses") | M3: =HYPERLINK("#'Deposits'!A1", "💰 Deposits") | O3: =HYPERLINK("#'bKash Transactions'!A1", "📱 bKash Audit")
A4: Note: Columns in Teal (H to O) contain dynamic EXCEL FORMULAS. Do not manually edit them.
A9: Member ID | B9: Name | C9: Room No | D9: Phone No | E9: Role | F9: Free Meal? | G9: Opening Balance (BDT) | H9: Home Meal Units | I9: Active Days | J9: Guest Meal Cost (BDT) | K9: Manager Fees (BDT) | L9: Meal Cost (BDT) | M9: Total Deposits (BDT) | N9: Total Bill (BDT) | O9: Closing Balance (BDT)
A10: 1 | B10: System Super Admin | D10: 01711223344 | E10: superadmin | F10: No | G10: 0 | H10: =IFERROR(VLOOKUP(A10, 'Meals Grid'!$A$8:$AR$1000, 42, FALSE), 0) | I10: =IFERROR(VLOOKUP(A10, 'Meals Grid'!$A$8:$AR$1000, 43, FALSE), 0) | J10: =IFERROR(VLOOKUP(A10, 'Meals Grid'!$A$8:$AR$1000, 44, FALSE), 0) * Setup!$C$9 | K10: =IF(F10="Yes", 0, I10 * Setup!$C$10) | L10: =IF(F10="Yes", 0, H10 * Dashboard!$C$9) | M10: =SUMIF(Deposits!$B$7:$B$1000, A10, Deposits!$D$7:$D$1000) | N10: =J10+K10+L10 | O10: =G10+M10-N10
A11: 4 | B11: Kamrul Islam | C11: 102 | D11: 01511223344 | E11: student | F11: No | G11: 1500 | H11: =IFERROR(VLOOKUP(A11, 'Meals Grid'!$A$8:$AR$1000, 42, FALSE), 0) | I11: =IFERROR(VLOOKUP(A11, 'Meals Grid'!$A$8:$AR$1000, 43, FALSE), 0) | J11: =IFERROR(VLOOKUP(A11, 'Meals Grid'!$A$8:$AR$1000, 44, FALSE), 0) * Setup!$C$9 | K11: =IF(F11="Yes", 0, I11 * Setup!$C$10) | L11: =IF(F11="Yes", 0, H11 * Dashboard!$C$9) | M11: =SUMIF(Deposits!$B$7:$B$1000, A11, Deposits!$D$7:$D$1000) | N11: =J11+K11+L11 | O11: =G11+M11-N11
A12: 5 | B12: Rakib Hasan | C12: 103 | D12: 01611223344 | E12: student | F12: No | G12: 2000 | H12: =IFERROR(VLOOKUP(A12, 'Meals Grid'!$A$8:$AR$1000, 42, FALSE), 0) | I12: =IFERROR(VLOOKUP(A12, 'Meals Grid'!$A$8:$AR$1000, 43, FALSE), 0) | J12: =IFERROR(VLOOKUP(A12, 'Meals Grid'!$A$8:$AR$1000, 44, FALSE), 0) * Setup!$C$9 | K12: =IF(F12="Yes", 0, I12 * Setup!$C$10) | L12: =IF(F12="Yes", 0, H12 * Dashboard!$C$9) | M12: =SUMIF(Deposits!$B$7:$B$1000, A12, Deposits!$D$7:$D$1000) | N12: =J12+K12+L12 | O12: =G12+M12-N12
A13: 2 | B13: Sabbir Ahmed (Mukti Mgr) | C13: 302 | D13: 01911223344 | E13: manager | F13: Yes | G13: 1566 | H13: =IFERROR(VLOOKUP(A13, 'Meals Grid'!$A$8:$AR$1000, 42, FALSE), 0) | I13: =IFERROR(VLOOKUP(A13, 'Meals Grid'!$A$8:$AR$1000, 43, FALSE), 0) | J13: =IFERROR(VLOOKUP(A13, 'Meals Grid'!$A$8:$AR$1000, 44, FALSE), 0) * Setup!$C$9 | K13: =IF(F13="Yes", 0, I13 * Setup!$C$10) | L13: =IF(F13="Yes", 0, H13 * Dashboard!$C$9) | M13: =SUMIF(Deposits!$B$7:$B$1000, A13, Deposits!$D$7:$D$1000) | N13: =J13+K13+L13 | O13: =G13+M13-N13
A14: 7 | B14: khoka moni | C14: 208 | D14: 01521769018 | E14: manager | F14: No | G14: 1000 | H14: =IFERROR(VLOOKUP(A14, 'Meals Grid'!$A$8:$AR$1000, 42, FALSE), 0) | I14: =IFERROR(VLOOKUP(A14, 'Meals Grid'!$A$8:$AR$1000, 43, FALSE), 0) | J14: =IFERROR(VLOOKUP(A14, 'Meals Grid'!$A$8:$AR$1000, 44, FALSE), 0) * Setup!$C$9 | K14: =IF(F14="Yes", 0, I14 * Setup!$C$10) | L14: =IF(F14="Yes", 0, H14 * Dashboard!$C$9) | M14: =SUMIF(Deposits!$B$7:$B$1000, A14, Deposits!$D$7:$D$1000) | N14: =J14+K14+L14 | O14: =G14+M14-N14
B15: Total | G15: =SUM(G10:G14) | H15: =SUM(H10:H14) | I15: =SUM(I10:I14) | J15: =SUM(J10:J14) | K15: =SUM(K10:K14) | L15: =SUM(L10:L14) | M15: =SUM(M10:M14) | N15: =SUM(N10:N14) | O15: =SUM(O10:O14)

Sheet Expenses
A1: Bazaar Expense Ledger
A2: Log daily purchases for cycle (2026-06-15 to 2026-06-30).
A3: =HYPERLINK("#'Instructions'!A1", "📖 Instructions") | C3: =HYPERLINK("#'Setup'!A1", "⚙️ Setup") | E3: =HYPERLINK("#'Dashboard'!A1", "📊 Dashboard") | G3: =HYPERLINK("#'Meals Grid'!A1", "🍽️ Meals Grid") | I3: =HYPERLINK("#'Members & Balances'!A1", "👥 Members") | K3: =HYPERLINK("#'Expenses'!A1", "🛒 Expenses") | M3: =HYPERLINK("#'Deposits'!A1", "💰 Deposits") | O3: =HYPERLINK("#'bKash Transactions'!A1", "📱 bKash Audit")
A6: Date | B6: Item Description | C6: Quantity | D6: Unit | E6: Amount (BDT)
A7: 2026-06-15 | B7: rice | C7: 2 | D7: kg | E7: 155
A8: 2026-06-15 | B8: murgi | C8: 10 | D8: kg | E8: 5000
B30: Total Expenses | E30: =SUM(E7:E29)

Sheet Deposits
A1: Student Deposit Ledger
A2: Log student meal payments (Cash / Bank / bKash) for cycle (2026-06-15 to 2026-06-30).
A3: =HYPERLINK("#'Instructions'!A1", "📖 Instructions") | C3: =HYPERLINK("#'Setup'!A1", "⚙️ Setup") | E3: =HYPERLINK("#'Dashboard'!A1", "📊 Dashboard") | G3: =HYPERLINK("#'Meals Grid'!A1", "🍽️ Meals Grid") | I3: =HYPERLINK("#'Members & Balances'!A1", "👥 Members") | K3: =HYPERLINK("#'Expenses'!A1", "🛒 Expenses") | M3: =HYPERLINK("#'Deposits'!A1", "💰 Deposits") | O3: =HYPERLINK("#'bKash Transactions'!A1", "📱 bKash Audit")
A4: Note: Column B (Member ID) uses a dropdown list of valid members. Column C (Name) auto-fills via formula.
A6: Date | B6: Member ID | C6: Name (Auto) | D6: Amount (BDT) | E6: Description / Transaction Ref
A7: 2026-06-15 | B7: 7 | C7: =IFERROR(VLOOKUP(B7, 'Members & Balances'!$A$10:$B$1000, 2, FALSE), "") | D7: 1000 | E7: cash
A8: 2026-06-15 | B8: 2 | C8: =IFERROR(VLOOKUP(B8, 'Members & Balances'!$A$10:$B$1000, 2, FALSE), "") | D8: 500 | E8: bKash Send Money (Sender: 01711223344, TrxID: ZZCNQOFS27)
A9: 2026-06-15 | B9: 2 | C9: =IFERROR(VLOOKUP(B9, 'Members & Balances'!$A$10:$B$1000, 2, FALSE), "") | D9: 566 | E9: bKash Send Money (Sender: Manager, TrxID: FSDFSADFWE)
C10: =IFERROR(VLOOKUP(B10, 'Members & Balances'!$A$10:$B$1000, 2, FALSE), "")
C11: =IFERROR(VLOOKUP(B11, 'Members & Balances'!$A$10:$B$1000, 2, FALSE), "")
C12: =IFERROR(VLOOKUP(B12, 'Members & Balances'!$A$10:$B$1000, 2, FALSE), "")
C13: =IFERROR(VLOOKUP(B13, 'Members & Balances'!$A$10:$B$1000, 2, FALSE), "")
C14: =IFERROR(VLOOKUP(B14, 'Members & Balances'!$A$10:$B$1000, 2, FALSE), "")
C15: =IFERROR(VLOOKUP(B15, 'Members & Balances'!$A$10:$B$1000, 2, FALSE), "")
C16: =IFERROR(VLOOKUP(B16, 'Members & Balances'!$A$10:$B$1000, 2, FALSE), "")
C17: =IFERROR(VLOOKUP(B17, 'Members & Balances'!$A$10:$B$1000, 2, FALSE), "")
C18: =IFERROR(VLOOKUP(B18, 'Members & Balances'!$A$10:$B$1000, 2, FALSE), "")
C19: =IFERROR(VLOOKUP(B19, 'Members & Balances'!$A$10:$B$1000, 2, FALSE), "")
C20: =IFERROR(VLOOKUP(B20, 'Members & Balances'!$A$10:$B$1000, 2, FALSE), "")
C21: =IFERROR(VLOOKUP(B21, 'Members & Balances'!$A$10:$B$1000, 2, FALSE), "")
... C29: =IFERROR(VLOOKUP(B29, 'Members & Balances'!$A$10:$B$1000, 2, FALSE), "")
B30: Total Deposits | D30: =SUM(D7:D29)

Sheet bKash Transactions
A1: bKash SMS Transaction database & Claims Auditor
A2: Verification system matches bKash SMS logs with student claims in the Deposits logbook.
A3: =HYPERLINK("#'Instructions'!A1", "📖 Instructions") | C3: =HYPERLINK("#'Setup'!A1", "⚙️ Setup") | E3: =HYPERLINK("#'Dashboard'!A1", "📊 Dashboard") | G3: =HYPERLINK("#'Meals Grid'!A1", "🍽️ Meals Grid") | I3: =HYPERLINK("#'Members & Balances'!A1", "👥 Members") | K3: =HYPERLINK("#'Expenses'!A1", "🛒 Expenses") | M3: =HYPERLINK("#'Deposits'!A1", "💰 Deposits") | O3: =HYPERLINK("#'bKash Transactions'!A1", "📱 bKash Audit")
A4: Note: Columns F to I contain formulas checking Deposits. Do not manually edit them.
A6: Transaction ID | B6: Sender Mobile | C6: SMS Amount (BDT) | D6: Date Received | E6: SMS Message Text | F6: Claimed By ID | G6: Claimed By Name | H6: Claim Status | I6: Verification Result
A7: ZZCNQOFS27 | B7: 01711223344 | C7: 500 | D7: 2026-06-15 | E7: You have received send money Tk 500.00 from 01711223344. TrxID ZZCNQOFS27 at 15/06/2026 16:44 | F7: =IFERROR(INDEX(Deposits!$B$7:$B$1000, MATCH(A7, Deposits!$E$7:$E$1000, 0)), "") | G7: =IF(F7="","",IFERROR(VLOOKUP(F7, 'Members & Balances'!$A$10:$B$1000, 2, FALSE), "Unknown Member")) | H7: =IF(F7="","Unclaimed","Claimed") | I7: =IF(F7="","",IF(IFERROR(INDEX(Deposits!$D$7:$D$1000, MATCH(A7, Deposits!$E$7:$E$1000, 0)), 0)=C7,"Verified","Amount Mismatch!"))
A8: FSDFSADFWE | B8: Manager | C8: 566 | D8: 2026-06-15 | E8: Manually added by Manager (mukti_mgr) | F8: =IFERROR(INDEX(Deposits!$B$7:$B$1000, MATCH(A8, Deposits!$E$7:$E$1000, 0)), "") | G8: =IF(F8="","",IFERROR(VLOOKUP(F8, 'Members & Balances'!$A$10:$B$1000, 2, FALSE), "Unknown Member")) | H8: =IF(F8="","Unclaimed","Claimed") | I8: =IF(F8="","",IF(IFERROR(INDEX(Deposits!$D$7:$D$1000, MATCH(A8, Deposits!$E$7:$E$1000, 0)), 0)=C8,"Verified","Amount Mismatch!"))
F9: =IFERROR(INDEX(Deposits!$B$7:$B$1000, MATCH(A9, Deposits!$E$7:$E$1000, 0)), "") | G9: =IF(F9="","",IFERROR(VLOOKUP(F9, 'Members & Balances'!$A$10:$B$1000, 2, FALSE), "Unknown Member")) | H9: =IF(F9="","Unclaimed","Claimed") | I9: =IF(F9="","",IF(IFERROR(INDEX(Deposits!$D$7:$D$1000, MATCH(A9, Deposits!$E$7:$E$1000, 0)), 0)=C9,"Verified","Amount Mismatch!"))
F10: =IFERROR(INDEX(Deposits!$B$7:$B$1000, MATCH(A10, Deposits!$E$7:$E$1000, 0)), "") | G10: =IF(F10="","",IFERROR(VLOOKUP(F10, 'Members & Balances'!$A$10:$B$1000, 2, FALSE), "Unknown Member")) | H10: =IF(F10="","Unclaimed","Claimed") | I10: =IF(F10="","",IF(IFERROR(INDEX(Deposits!$D$7:$D$1000, MATCH(A10, Deposits!$E$7:$E$1000, 0)), 0)=C10,"Verified","Amount Mismatch!"))
F11: =IFERROR(INDEX(Deposits!$B$7:$B$1000, MATCH(A11, Deposits!$E$7:$E$1000, 0)), "") | G11: =IF(F11="","",IFERROR(VLOOKUP(F11, 'Members & Balances'!$A$10:$B$1000, 2, FALSE), "Unknown Member")) | H11: =IF(F11="","Unclaimed","Claimed") | I11: =IF(F11="","",IF(IFERROR(INDEX(Deposits!$D$7:$D$1000, MATCH(A11, Deposits!$E$7:$E$1000, 0)), 0)=C11,"Verified","Amount Mismatch!"))
F12: =IFERROR(INDEX(Deposits!$B$7:$B$1000, MATCH(A12, Deposits!$E$7:$E$1000, 0)), "") | G12: =IF(F12="","",IFERROR(VLOOKUP(F12, 'Members & Balances'!$A$10:$B$1000, 2, FALSE), "Unknown Member")) | H12: =IF(F12="","Unclaimed","Claimed") | I12: =IF(F12="","",IF(IFERROR(INDEX(Deposits!$D$7:$D$1000, MATCH(A12, Deposits!$E$7:$E$1000, 0)), 0)=C12,"Verified","Amount Mismatch!"))
F13: =IFERROR(INDEX(Deposits!$B$7:$B$1000, MATCH(A13, Deposits!$E$7:$E$1000, 0)), "") | G13: =IF(F13="","",IFERROR(VLOOKUP(F13, 'Members & Balances'!$A$10:$B$1000, 2, FALSE), "Unknown Member")) | H13: =IF(F13="","Unclaimed","Claimed") | I13: =IF(F13="","",IF(IFERROR(INDEX(Deposits!$D$7:$D$1000, MATCH(A13, Deposits!$E$7:$E$1000, 0)), 0)=C13,"Verified","Amount Mismatch!"))
F14: =IFERROR(INDEX(Deposits!$B$7:$B$1000, MATCH(A14, Deposits!$E$7:$E$1000, 0)), "") | G14: =IF(F14="","",IFERROR(VLOOKUP(F14, 'Members & Balances'!$A$10:$B$1000, 2, FALSE), "Unknown Member")) | H14: =IF(F14="","Unclaimed","Claimed") | I14: =IF(F14="","",IF(IFERROR(INDEX(Deposits!$D$7:$D$1000, MATCH(A14, Deposits!$E$7:$E$1000, 0)), 0)=C14,"Verified","Amount Mismatch!"))
F15: =IFERROR(INDEX(Deposits!$B$7:$B$1000, MATCH(A15, Deposits!$E$7:$E$1000, 0)), "") | G15: =IF(F15="","",IFERROR(VLOOKUP(F15, 'Members & Balances'!$A$10:$B$1000, 2, FALSE), "Unknown Member")) | H15: =IF(F15="","Unclaimed","Claimed") | I15: =IF(F15="","",IF(IFERROR(INDEX(Deposits!$D$7:$D$1000, MATCH(A15, Deposits!$E$7:$E$1000, 0)), 0)=C15,"Verified","Amount Mismatch!"))
F16: =IFERROR(INDEX(Deposits!$B$7:$B$1000, MATCH(A16, Deposits!$E$7:$E$1000, 0)), "") | G16: =IF(F16="","",IFERROR(VLOOKUP(F16, 'Members & Balances'!$A$10:$B$1000, 2, FALSE), "Unknown Member")) | H16: =IF(F16="","Unclaimed","Claimed") | I16: =IF(F16="","",IF(IFERROR(INDEX(Deposits!$D$7:$D$1000, MATCH(A16, Deposits!$E$7:$E$1000, 0)), 0)=C16,"Verified","Amount Mismatch!"))
F17: =IFERROR(INDEX(Deposits!$B$7:$B$1000, MATCH(A17, Deposits!$E$7:$E$1000, 0)), "") | G17: =IF(F17="","",IFERROR(VLOOKUP(F17, 'Members & Balances'!$A$10:$B$1000, 2, FALSE), "Unknown Member")) | H17: =IF(F17="","Unclaimed","Claimed") | I17: =IF(F17="","",IF(IFERROR(INDEX(Deposits!$D$7:$D$1000, MATCH(A17, Deposits!$E$7:$E$1000, 0)), 0)=C17,"Verified","Amount Mismatch!"))
F18: =IFERROR(INDEX(Deposits!$B$7:$B$1000, MATCH(A18, Deposits!$E$7:$E$1000, 0)), "") | G18: =IF(F18="","",IFERROR(VLOOKUP(F18, 'Members & Balances'!$A$10:$B$1000, 2, FALSE), "Unknown Member")) | H18: =IF(F18="","Unclaimed","Claimed") | I18: =IF(F18="","",IF(IFERROR(INDEX(Deposits!$D$7:$D$1000, MATCH(A18, Deposits!$E$7:$E$1000, 0)), 0)=C18,"Verified","Amount Mismatch!"))
F19: =IFERROR(INDEX(Deposits!$B$7:$B$1000, MATCH(A19, Deposits!$E$7:$E$1000, 0)), "") | G19: =IF(F19="","",IFERROR(VLOOKUP(F19, 'Members & Balances'!$A$10:$B$1000, 2, FALSE), "Unknown Member")) | H19: =IF(F19="","Unclaimed","Claimed") | I19: =IF(F19="","",IF(IFERROR(INDEX(Deposits!$D$7:$D$1000, MATCH(A19, Deposits!$E$7:$E$1000, 0)), 0)=C19,"Verified","Amount Mismatch!"))
F20: =IFERROR(INDEX(Deposits!$B$7:$B$1000, MATCH(A20, Deposits!$E$7:$E$1000, 0)), "") | G20: =IF(F20="","",IFERROR(VLOOKUP(F20, 'Members & Balances'!$A$10:$B$1000, 2, FALSE), "Unknown Member")) | H20: =IF(F20="","Unclaimed","Claimed") | I20: =IF(F20="","",IF(IFERROR(INDEX(Deposits!$D$7:$D$1000, MATCH(A20, Deposits!$E$7:$E$1000, 0)), 0)=C20,"Verified","Amount Mismatch!"))
... F23: =IFERROR(INDEX(Deposits!$B$7:$B$1000, MATCH(A23, Deposits!$E$7:$E$1000, 0)), "") | G23: =IF(F23="","",IFERROR(VLOOKUP(F23, 'Members & Balances'!$A$10:$B$1000, 2, FALSE), "Unknown Member")) | H23: =IF(F23="","Unclaimed","Claimed") | I23: =IF(F23="","",IF(IFERROR(INDEX(Deposits!$D$7:$D$1000, MATCH(A23, Deposits!$E$7:$E$1000, 0)), 0)=C23,"Verified","Amount Mismatch!"))
